ATV2/Mux.v
/* Módulo MUX */
`ifndef _Mux_
`define _Mux_

module Mux (out, a, b, sel);
  input a,b,sel; 
  output out;
  wire w1,w2,w3;

  //Descrição
  nand nand0(w1,a,w3);
  nand nand1(w2,b,sel);
  nand nand2(out,w1,w2);
  not not0(w3, sel);

endmodule
`endif

ATV1/TESTBENCH/tb_Mux.v
/* testbench para Mux */
/* ordem de portas: out, a, b, sel */
/* input a; input b; input sel; */
/* output out; */

`include "Mux.v"

`define assert(signal, value) \
    if (signal !== value) \
    begin \
        $display("ASSERTION FAILED in %m: signal != value"); \
        $finish; \
    end else begin \
        $display("Success! %m: signal = value"); \
    end
    

module tb_Mux;
    reg a;
    reg b;
    reg sel;
    wire out;

    Mux mymodule(out, a, b, sel);
    
    initial
    begin
        $dumpfile("tb_Mux.vcd");
        $dumpvars(0, tb_Mux);

        a = 1'b0; b = 1'b0; sel = 1'b0; #1;
         `assert(out, 1'b0)
        a = 1'b0; b = 1'b0; sel = 1'b1; #1;
         `assert(out, 1'b0)
        a = 1'b0; b = 1'b1; sel = 1'b0; #1;
         `assert(out, 1'b0)
        a = 1'b0; b = 1'b1; sel = 1'b1; #1;
         `assert(out, 1'b1)
        a = 1'b1; b = 1'b0; sel = 1'b0; #1;
         `assert(out, 1'b1)
        a = 1'b1; b = 1'b0; sel = 1'b1; #1;
         `assert(out, 1'b0)
        a = 1'b1; b = 1'b1; sel = 1'b0; #1;
         `assert(out, 1'b1)
        a = 1'b1; b = 1'b1; sel = 1'b1; #1;
         `assert(out, 1'b1)

    end
endmodule

ATV1/TESTBENCH/tb_Mux.vcd
$date
	Wed Mar 29 16:31:55 2023
$end
$version
	Icarus Verilog
$end
$timescale
	1s
$end
$scope module tb_Mux $end
$var wire 1 ! out $end
$var reg 1 " a $end
$var reg 1 # b $end
$var reg 1 $ sel $end
$scope module mymodule $end
$var wire 1 " a $end
$var wire 1 # b $end
$var wire 1 ! out $end
$var wire 1 $ sel $end
$var wire 1 % w1 $end
$var wire 1 & w2 $end
$var wire 1 ' w3 $end
$upscope $end
$upscope $end
$enddefinitions $end
$comment Show the parameter values. $end
$dumpall
$end
#0
$dumpvars
1'
1&
1%
0$
0#
0"
0!
$end
#1
0'
1$
#2
1'
0$
1#
#3
1!
0&
0'
1$
#4
0%
1!
1'
1&
0$
0#
1"
#5
0!
1%
0'
1$
#6
1!
0%
1'
0$
1#
#7
1%
0&
0'
1$
